{
  "families": [
    {
      "id": "qwl",
      "root": "ق و ل",
      "rootTr": "q-w-l",
      "theme": "to say — the most frequent verb in the Quran (about 1,700 occurrences)",
      "storyRef": { "story": "story-03", "ar": "يَقُولُ" },
      "members": [
        { "ar": "قَالَ", "tr": "qāla", "en": "he said" },
        { "ar": "قَالُوا", "tr": "qālū", "en": "they said" },
        { "ar": "يَقُولُ", "tr": "yaqūlu", "en": "he says" },
        { "ar": "يَقُولُونَ", "tr": "yaqūlūna", "en": "they say" },
        { "ar": "قُلْ", "tr": "qul", "en": "say! (command)" },
        { "ar": "قَوْل", "tr": "qawl", "en": "saying, speech" },
        { "ar": "قِيلَ", "tr": "qīla", "en": "it was said" }
      ],
      "quran": [
        { "ref": "112:1", "ar": "قُلْ هُوَ اللَّهُ أَحَدٌ", "en": "Say: He is Allah, the One." },
        { "ref": "2:30", "ar": "وَإِذْ قَالَ رَبُّكَ لِلْمَلَائِكَةِ إِنِّي جَاعِلٌ فِي الْأَرْضِ خَلِيفَةً", "en": "And when your Lord said to the angels: Indeed I will place a successor upon the earth." }
      ]
    },
    {
      "id": "qra",
      "root": "ق ر أ",
      "rootTr": "q-r-ʾ",
      "theme": "to read, recite — the root of القُرْآن itself",
      "storyRef": { "story": "story-01", "ar": "أَقْرَأُ" },
      "members": [
        { "ar": "قَرَأَ", "tr": "qaraʾa", "en": "he read, recited" },
        { "ar": "يَقْرَأُ", "tr": "yaqraʾu", "en": "he reads" },
        { "ar": "اِقْرَأْ", "tr": "iqraʾ", "en": "read! (the first revealed word)" },
        { "ar": "قُرْآن", "tr": "qurʾān", "en": "Quran; recitation" },
        { "ar": "قِرَاءَة", "tr": "qirāʾa", "en": "reading, recitation" }
      ],
      "quran": [
        { "ref": "96:1", "ar": "اقْرَأْ بِاسْمِ رَبِّكَ الَّذِي خَلَقَ", "en": "Read in the name of your Lord who created." },
        { "ref": "12:2", "ar": "إِنَّا أَنزَلْنَاهُ قُرْآنًا عَرَبِيًّا لَّعَلَّكُمْ تَعْقِلُونَ", "en": "Indeed, We sent it down as an Arabic Quran that you might understand." }
      ]
    },
    {
      "id": "ktb",
      "root": "ك ت ب",
      "rootTr": "k-t-b",
      "theme": "to write, decree — الكِتَاب is the Quran's name for itself",
      "storyRef": { "story": "story-01", "ar": "كِتَابًا" },
      "members": [
        { "ar": "كَتَبَ", "tr": "kataba", "en": "he wrote; he decreed" },
        { "ar": "يَكْتُبُ", "tr": "yaktubu", "en": "he writes" },
        { "ar": "كُتِبَ", "tr": "kutiba", "en": "it was prescribed, decreed" },
        { "ar": "كِتَاب", "tr": "kitāb", "en": "book, scripture" },
        { "ar": "كُتُب", "tr": "kutub", "en": "books" },
        { "ar": "مَكْتُوب", "tr": "maktūb", "en": "written" }
      ],
      "quran": [
        { "ref": "2:2", "ar": "ذَٰلِكَ الْكِتَابُ لَا رَيْبَ فِيهِ", "en": "This is the Book about which there is no doubt." },
        { "ref": "2:183", "ar": "كُتِبَ عَلَيْكُمُ الصِّيَامُ كَمَا كُتِبَ عَلَى الَّذِينَ مِن قَبْلِكُمْ", "en": "Fasting has been prescribed for you as it was prescribed for those before you." }
      ]
    },
    {
      "id": "3lm",
      "root": "ع ل م",
      "rootTr": "ʿ-l-m",
      "theme": "to know — knowledge, the All-Knowing, and your story's مُعَلِّمَة",
      "storyRef": { "story": "story-02", "ar": "مُعَلِّمَة" },
      "members": [
        { "ar": "عَلِمَ", "tr": "ʿalima", "en": "he knew" },
        { "ar": "يَعْلَمُ", "tr": "yaʿlamu", "en": "he knows" },
        { "ar": "عَلَّمَ", "tr": "ʿallama", "en": "he taught" },
        { "ar": "عِلْم", "tr": "ʿilm", "en": "knowledge" },
        { "ar": "عَلِيم", "tr": "ʿalīm", "en": "All-Knowing (of Allah)" },
        { "ar": "عَالِم", "tr": "ʿālim", "en": "knower, scholar" },
        { "ar": "مُعَلِّم", "tr": "muʿallim", "en": "teacher" }
      ],
      "quran": [
        { "ref": "96:5", "ar": "عَلَّمَ الْإِنسَانَ مَا لَمْ يَعْلَمْ", "en": "He taught man that which he knew not." },
        { "ref": "2:282", "ar": "وَاللَّهُ بِكُلِّ شَيْءٍ عَلِيمٌ", "en": "And Allah is Knowing of all things." }
      ]
    },
    {
      "id": "3ml",
      "root": "ع م ل",
      "rootTr": "ʿ-m-l",
      "theme": "to do, work — the Quran constantly pairs faith with deeds",
      "storyRef": { "story": "story-01", "ar": "أَعْمَلُ" },
      "members": [
        { "ar": "عَمِلَ", "tr": "ʿamila", "en": "he did, worked" },
        { "ar": "عَمِلُوا", "tr": "ʿamilū", "en": "they did" },
        { "ar": "يَعْمَلُ", "tr": "yaʿmalu", "en": "he does" },
        { "ar": "يَعْمَلُونَ", "tr": "yaʿmalūna", "en": "they do" },
        { "ar": "عَمَل", "tr": "ʿamal", "en": "deed, work" },
        { "ar": "أَعْمَال", "tr": "aʿmāl", "en": "deeds" }
      ],
      "quran": [
        { "ref": "2:82", "ar": "وَالَّذِينَ آمَنُوا وَعَمِلُوا الصَّالِحَاتِ أُولَٰئِكَ أَصْحَابُ الْجَنَّةِ", "en": "Those who believe and do righteous deeds — they are the companions of Paradise." },
        { "ref": "99:7", "ar": "فَمَن يَعْمَلْ مِثْقَالَ ذَرَّةٍ خَيْرًا يَرَهُ", "en": "So whoever does an atom's weight of good will see it." }
      ]
    },
    {
      "id": "akl",
      "root": "أ ك ل",
      "rootTr": "ʾ-k-l",
      "theme": "to eat — from your breakfast story to the garden of Adam",
      "storyRef": { "story": "story-01", "ar": "آكُلُ" },
      "members": [
        { "ar": "أَكَلَ", "tr": "akala", "en": "he ate" },
        { "ar": "يَأْكُلُ", "tr": "yaʾkulu", "en": "he eats" },
        { "ar": "يَأْكُلُونَ", "tr": "yaʾkulūna", "en": "they eat" },
        { "ar": "كُلُوا", "tr": "kulū", "en": "eat! (plural command)" },
        { "ar": "أَكْل", "tr": "akl", "en": "eating, food" }
      ],
      "quran": [
        { "ref": "2:172", "ar": "يَا أَيُّهَا الَّذِينَ آمَنُوا كُلُوا مِن طَيِّبَاتِ مَا رَزَقْنَاكُمْ", "en": "O you who believe, eat from the good things We have provided you." },
        { "ref": "2:35", "ar": "وَكُلَا مِنْهَا رَغَدًا حَيْثُ شِئْتُمَا", "en": "And eat from it freely, wherever you two wish." }
      ]
    },
    {
      "id": "shrb",
      "root": "ش ر ب",
      "rootTr": "sh-r-b",
      "theme": "to drink — paired with أكل in the Quran's commands",
      "storyRef": { "story": "story-01", "ar": "أَشْرَبُ" },
      "members": [
        { "ar": "شَرِبَ", "tr": "shariba", "en": "he drank" },
        { "ar": "يَشْرَبُ", "tr": "yashrabu", "en": "he drinks" },
        { "ar": "اِشْرَبُوا", "tr": "ishrabū", "en": "drink! (plural command)" },
        { "ar": "شَرَاب", "tr": "sharāb", "en": "drink, beverage" },
        { "ar": "مَشْرَب", "tr": "mashrab", "en": "drinking place" }
      ],
      "quran": [
        { "ref": "7:31", "ar": "وَكُلُوا وَاشْرَبُوا وَلَا تُسْرِفُوا", "en": "And eat and drink, but do not be excessive." },
        { "ref": "16:69", "ar": "يَخْرُجُ مِن بُطُونِهَا شَرَابٌ مُّخْتَلِفٌ أَلْوَانُهُ", "en": "From their bellies comes a drink of varying colors." }
      ]
    },
    {
      "id": "dhhb",
      "root": "ذ هـ ب",
      "rootTr": "dh-h-b",
      "theme": "to go — and the same letters spell ذَهَب, gold",
      "storyRef": { "story": "story-01", "ar": "أَذْهَبُ" },
      "members": [
        { "ar": "ذَهَبَ", "tr": "dhahaba", "en": "he went; took away" },
        { "ar": "يَذْهَبُ", "tr": "yadhhabu", "en": "he goes" },
        { "ar": "اِذْهَبْ", "tr": "idhhab", "en": "go! (command)" },
        { "ar": "ذَاهِب", "tr": "dhāhib", "en": "going (active participle)" },
        { "ar": "ذَهَب", "tr": "dhahab", "en": "gold" }
      ],
      "quran": [
        { "ref": "20:24", "ar": "اذْهَبْ إِلَىٰ فِرْعَوْنَ إِنَّهُ طَغَىٰ", "en": "Go to Pharaoh; indeed he has transgressed." },
        { "ref": "2:17", "ar": "ذَهَبَ اللَّهُ بِنُورِهِمْ وَتَرَكَهُمْ فِي ظُلُمَاتٍ", "en": "Allah took away their light and left them in darkness." }
      ]
    },
    {
      "id": "slw",
      "root": "ص ل و",
      "rootTr": "ṣ-l-w",
      "theme": "prayer — from your morning صلاة الفجر to the Quran's command",
      "storyRef": { "story": "story-01", "ar": "أُصَلِّي" },
      "members": [
        { "ar": "صَلَّى", "tr": "ṣallā", "en": "he prayed" },
        { "ar": "يُصَلِّي", "tr": "yuṣallī", "en": "he prays" },
        { "ar": "صَلِّ", "tr": "ṣalli", "en": "pray! (command)" },
        { "ar": "صَلَاة", "tr": "ṣalāh", "en": "prayer" },
        { "ar": "صَلَوَات", "tr": "ṣalawāt", "en": "prayers" }
      ],
      "quran": [
        { "ref": "2:43", "ar": "وَأَقِيمُوا الصَّلَاةَ وَآتُوا الزَّكَاةَ", "en": "And establish prayer and give zakah." },
        { "ref": "108:2", "ar": "فَصَلِّ لِرَبِّكَ وَانْحَرْ", "en": "So pray to your Lord and sacrifice." }
      ]
    },
    {
      "id": "hbb",
      "root": "ح ب ب",
      "rootTr": "ḥ-b-b",
      "theme": "to love — whom Allah loves, and loving Allah",
      "storyRef": { "story": "story-02", "ar": "أُحِبُّ" },
      "members": [
        { "ar": "أَحَبَّ", "tr": "aḥabba", "en": "he loved" },
        { "ar": "يُحِبُّ", "tr": "yuḥibbu", "en": "he loves" },
        { "ar": "تُحِبُّونَ", "tr": "tuḥibbūna", "en": "you (pl.) love" },
        { "ar": "حُبّ", "tr": "ḥubb", "en": "love" },
        { "ar": "مَحَبَّة", "tr": "maḥabba", "en": "love, affection" }
      ],
      "quran": [
        { "ref": "3:31", "ar": "قُلْ إِن كُنتُمْ تُحِبُّونَ اللَّهَ فَاتَّبِعُونِي يُحْبِبْكُمُ اللَّهُ", "en": "Say: If you love Allah, then follow me — Allah will love you." },
        { "ref": "2:195", "ar": "إِنَّ اللَّهَ يُحِبُّ الْمُحْسِنِينَ", "en": "Indeed, Allah loves the doers of good." }
      ]
    },
    {
      "id": "sal",
      "root": "س أ ل",
      "rootTr": "s-ʾ-l",
      "theme": "to ask — يَسْأَلُونَكَ 'they ask you' opens many Quranic passages",
      "storyRef": { "story": "story-03", "ar": "تَسْأَلُ" },
      "members": [
        { "ar": "سَأَلَ", "tr": "saʾala", "en": "he asked" },
        { "ar": "يَسْأَلُ", "tr": "yasʾalu", "en": "he asks" },
        { "ar": "يَسْأَلُونَكَ", "tr": "yasʾalūnaka", "en": "they ask you" },
        { "ar": "يَتَسَاءَلُونَ", "tr": "yatasāʾalūna", "en": "they ask one another" },
        { "ar": "سُؤَال", "tr": "suʾāl", "en": "question" }
      ],
      "quran": [
        { "ref": "78:1", "ar": "عَمَّ يَتَسَاءَلُونَ", "en": "About what do they ask one another?" },
        { "ref": "4:32", "ar": "وَاسْأَلُوا اللَّهَ مِن فَضْلِهِ", "en": "And ask Allah of His bounty." }
      ]
    },
    {
      "id": "ywm",
      "root": "ي و م",
      "rootTr": "y-w-m",
      "theme": "day — from your daily routine to يَوْم الدِّين",
      "storyRef": { "story": "story-01", "ar": "يَوْمِي" },
      "members": [
        { "ar": "يَوْم", "tr": "yawm", "en": "day" },
        { "ar": "أَيَّام", "tr": "ayyām", "en": "days" },
        { "ar": "اليَوْم", "tr": "al-yawm", "en": "today" },
        { "ar": "يَوْمَئِذٍ", "tr": "yawmaʾidhin", "en": "on that Day" },
        { "ar": "يَوْم الدِّين", "tr": "yawm ad-dīn", "en": "the Day of Judgment" },
        { "ar": "يَوْم القِيَامَة", "tr": "yawm al-qiyāma", "en": "the Day of Resurrection" }
      ],
      "quran": [
        { "ref": "1:4", "ar": "مَالِكِ يَوْمِ الدِّينِ", "en": "Master of the Day of Judgment." },
        { "ref": "26:88", "ar": "يَوْمَ لَا يَنفَعُ مَالٌ وَلَا بَنُونَ", "en": "The Day when neither wealth nor children will benefit." }
      ]
    },
    {
      "id": "hyy",
      "root": "ح ي ي",
      "rootTr": "ḥ-y-y",
      "theme": "life — الدُّنْيَا, resurrection, and الحَيّ the Ever-Living",
      "storyRef": { "story": "story-02", "ar": "حَيَاتِي" },
      "members": [
        { "ar": "حَيَاة", "tr": "ḥayāh", "en": "life" },
        { "ar": "الحَيَاة الدُّنْيَا", "tr": "al-ḥayāh ad-dunyā", "en": "the worldly life" },
        { "ar": "حَيّ", "tr": "ḥayy", "en": "alive, living" },
        { "ar": "الحَيّ", "tr": "al-Ḥayy", "en": "the Ever-Living (of Allah)" },
        { "ar": "يُحْيِي", "tr": "yuḥyī", "en": "He gives life" },
        { "ar": "أَحْيَا", "tr": "aḥyā", "en": "He gave life" }
      ],
      "quran": [
        { "ref": "21:30", "ar": "وَجَعَلْنَا مِنَ الْمَاءِ كُلَّ شَيْءٍ حَيٍّ", "en": "And We made from water every living thing." },
        { "ref": "2:258", "ar": "رَبِّيَ الَّذِي يُحْيِي وَيُمِيتُ", "en": "My Lord is the one who gives life and causes death." }
      ]
    },
    {
      "id": "klm",
      "root": "ك ل م",
      "rootTr": "k-l-m",
      "theme": "to speak — كَلِمَة a word, and Allah's speech to Musa",
      "storyRef": { "story": "story-01", "ar": "أَتَكَلَّمُ" },
      "members": [
        { "ar": "تَكَلَّمَ", "tr": "takallama", "en": "he spoke" },
        { "ar": "يَتَكَلَّمُ", "tr": "yatakallamu", "en": "he speaks" },
        { "ar": "كَلَّمَ", "tr": "kallama", "en": "he spoke to" },
        { "ar": "كَلِمَة", "tr": "kalima", "en": "word" },
        { "ar": "كَلِمَات", "tr": "kalimāt", "en": "words" },
        { "ar": "كَلَام", "tr": "kalām", "en": "speech" }
      ],
      "quran": [
        { "ref": "4:164", "ar": "وَكَلَّمَ اللَّهُ مُوسَىٰ تَكْلِيمًا", "en": "And Allah spoke to Musa directly." },
        { "ref": "14:24", "ar": "أَلَمْ تَرَ كَيْفَ ضَرَبَ اللَّهُ مَثَلًا كَلِمَةً طَيِّبَةً كَشَجَرَةٍ طَيِّبَةٍ", "en": "Do you not see how Allah presents the example of a good word — like a good tree?" }
      ]
    },
    {
      "id": "byt",
      "root": "ب ي ت",
      "rootTr": "b-y-t",
      "theme": "house — from your home to البَيْت, the Kaaba",
      "storyRef": { "story": "story-02", "ar": "بَيْتُنَا" },
      "members": [
        { "ar": "بَيْت", "tr": "bayt", "en": "house" },
        { "ar": "بُيُوت", "tr": "buyūt", "en": "houses" },
        { "ar": "البَيْت", "tr": "al-bayt", "en": "the House (the Kaaba)" },
        { "ar": "أَهْل البَيْت", "tr": "ahl al-bayt", "en": "the people of the house" }
      ],
      "quran": [
        { "ref": "2:125", "ar": "وَإِذْ جَعَلْنَا الْبَيْتَ مَثَابَةً لِّلنَّاسِ وَأَمْنًا", "en": "And when We made the House a place of return for the people and a sanctuary." },
        { "ref": "3:96", "ar": "إِنَّ أَوَّلَ بَيْتٍ وُضِعَ لِلنَّاسِ لَلَّذِي بِبَكَّةَ مُبَارَكًا", "en": "Indeed, the first House established for mankind was that at Bakkah — blessed." }
      ]
    }
  ]
}
